{
  "updatedAt": "2026-05-05T14:24:16.830Z",
  "createdAt": "2026-04-22T15:34:01.105Z",
  "id": "SDSoESzsSfL87W36",
  "name": "WMMA Manager Weekly Report Intake",
  "active": true,
  "isArchived": false,
  "nodes": [
    {
      "parameters": {
        "httpMethod": "POST",
        "path": "manager-weekly-report-intake",
        "responseMode": "responseNode",
        "options": {}
      },
      "id": "31cf6e68-c1ea-4702-a698-fd23dcd46724",
      "name": "Webhook",
      "type": "n8n-nodes-base.webhook",
      "typeVersion": 2,
      "position": [
        0,
        0
      ],
      "webhookId": "5540db84-f8fc-41ef-abb0-a2f02339555d"
    },
    {
      "parameters": {
        "jsCode": "\nconst body = $json.body ?? $json;\nconst portfolioMap = {\n  \"Breanna\": [\"Courtyard\", \"Adobe\", \"NorthPark\"],\n  \"Amy\": [\"Jefferson\", \"Riveredge\", \"Crosskeys\"],\n  \"Debbie\": [\"Sagebrush\"],\n  \"Dede\": [\"Westminster\", \"Broadstone\", \"Nelson\"],\n  \"Shelbie/Chris\": [\"Oak Terrace\"],\n  \"Ashlie\": [\"Single Families and Small Multi\"]\n};\n\nfunction isMonday(dateStr) {\n  const d = new Date(`${dateStr}T00:00:00`);\n  return !Number.isNaN(d.getTime()) && d.getDay() === 1;\n}\n\nfunction makeUuid() {\n  return 'xxxxxxxx-xxxx-4xxx-yxxx-xxxxxxxxxxxx'.replace(/[xy]/g, c => {\n    const r = Math.random() * 16 | 0;\n    const v = c === 'x' ? r : (r & 0x3 | 0x8);\n    return v.toString(16);\n  });\n}\n\nconst requiredTop = ['manager_name', 'week_start_date', 'submitted_at', 'properties'];\nfor (const field of requiredTop) {\n  if (!(field in body)) {\n    throw new Error(`Missing top-level field: ${field}`);\n  }\n}\n\nif (!portfolioMap[body.manager_name]) {\n  throw new Error(`Invalid manager_name: ${body.manager_name}`);\n}\n\nif (!isMonday(body.week_start_date)) {\n  throw new Error('week_start_date must be a Monday');\n}\n\nif (!Array.isArray(body.properties) || body.properties.length === 0) {\n  throw new Error('properties must be a non-empty array');\n}\n\nconst expectedProperties = new Set(portfolioMap[body.manager_name]);\nconst seenProperties = new Set();\n\nconst submittedAt = new Date(body.submitted_at);\nif (Number.isNaN(submittedAt.getTime())) {\n  throw new Error('submitted_at must be a valid ISO timestamp');\n}\n\nconst mondayCutoff = new Date(`${body.week_start_date}T10:00:00-05:00`);\nconst lateSubmission = submittedAt > mondayCutoff ? 1 : 0;\n\nconst rows = body.properties.map((row) => {\n  const requiredNumeric = [\n    'vacant_units',\n    'ready_vacants',\n    'not_ready_vacants',\n    'delinquent_count',\n    'delinquent_amount',\n    'turns_in_progress',\n    'work_orders_over_7_days'\n  ];\n  const requiredText = ['property_name', 'biggest_issue_text', 'help_needed_text'];\n\n  for (const field of requiredNumeric) {\n    if (!(field in row)) throw new Error(`Missing required numeric field: ${field}`);\n    const num = Number(row[field]);\n    if (Number.isNaN(num) || num < 0) throw new Error(`Invalid numeric value for ${field} on ${row.property_name}`);\n  }\n\n  for (const field of requiredText) {\n    if (!(field in row) || !String(row[field]).trim()) {\n      throw new Error(`Missing required text field: ${field} on ${row.property_name ?? 'unknown property'}`);\n    }\n  }\n\n  if (Number(row.vacant_units) !== Number(row.ready_vacants) + Number(row.not_ready_vacants)) {\n    throw new Error(`Vacancy split mismatch on ${row.property_name}`);\n  }\n\n  if (!expectedProperties.has(row.property_name)) {\n    throw new Error(`Property ${row.property_name} is not assigned to ${body.manager_name}`);\n  }\n  if (seenProperties.has(row.property_name)) {\n    throw new Error(`Duplicate property row: ${row.property_name}`);\n  }\n  seenProperties.add(row.property_name);\n\n  return {\n    id: makeUuid(),\n    manager_name: body.manager_name,\n    week_start_date: body.week_start_date,\n    property_name: row.property_name,\n    vacant_units: Number(row.vacant_units),\n    ready_vacants: Number(row.ready_vacants),\n    not_ready_vacants: Number(row.not_ready_vacants),\n    delinquent_count: Number(row.delinquent_count),\n    delinquent_amount: Number(Number(row.delinquent_amount).toFixed(2)),\n    turns_in_progress: Number(row.turns_in_progress),\n    work_orders_over_7_days: Number(row.work_orders_over_7_days),\n    biggest_issue_text: String(row.biggest_issue_text).trim(),\n    help_needed_text: String(row.help_needed_text).trim(),\n    struggling_units_text: row.struggling_units_text ? String(row.struggling_units_text).trim() : null,\n    late_submission: lateSubmission,\n    created_at: new Date().toISOString().slice(0, 19).replace('T', ' ')\n  };\n});\n\nfor (const property of expectedProperties) {\n  if (!seenProperties.has(property)) {\n    throw new Error(`Missing assigned property row: ${property}`);\n  }\n}\n\nreturn rows.map(r => ({ json: r }));\n"
      },
      "id": "36dc31fb-8992-4130-9320-c66c9225c684",
      "name": "Validate and Expand Rows",
      "type": "n8n-nodes-base.code",
      "typeVersion": 2,
      "position": [
        288,
        0
      ]
    },
    {
      "parameters": {
        "operation": "executeQuery",
        "query": "\nINSERT INTO manager_weekly_reports (\n  id,\n  manager_name,\n  week_start_date,\n  property_name,\n  vacant_units,\n  ready_vacants,\n  not_ready_vacants,\n  delinquent_count,\n  delinquent_amount,\n  turns_in_progress,\n  work_orders_over_7_days,\n  biggest_issue_text,\n  help_needed_text,\n  struggling_units_text,\n  late_submission,\n  created_at\n) VALUES (\n  $1,$2,$3,$4,$5,$6,$7,$8,$9,$10,$11,$12,$13,$14,$15,$16\n);\n",
        "options": {
          "queryReplacement": "={{\n[\n  $json.id,\n  $json.manager_name,\n  $json.week_start_date,\n  $json.property_name,\n  $json.vacant_units,\n  $json.ready_vacants,\n  $json.not_ready_vacants,\n  $json.delinquent_count,\n  $json.delinquent_amount,\n  $json.turns_in_progress,\n  $json.work_orders_over_7_days,\n  $json.biggest_issue_text,\n  $json.help_needed_text,\n  $json.struggling_units_text || null,\n  $json.late_submission,\n  $json.created_at\n]\n}}"
        }
      },
      "id": "708d1b45-6573-40c0-a4ea-28fa6c6ff12f",
      "name": "Insert Weekly Report Rows",
      "type": "n8n-nodes-base.mySql",
      "typeVersion": 2.5,
      "position": [
        768,
        0
      ],
      "credentials": {
        "mySql": {
          "id": "f3UzvmAj6M8o27XN",
          "name": "Blaze_Ops Database"
        }
      }
    },
    {
      "parameters": {
        "respondWith": "json",
        "responseBody": "={\"status\":\"ok\",\"rows_inserted\": {{$items().length}} }",
        "options": {}
      },
      "id": "f4b4c3d3-8a8b-4089-b28a-a6286eddda84",
      "name": "Respond Success",
      "type": "n8n-nodes-base.respondToWebhook",
      "typeVersion": 1.1,
      "position": [
        1072,
        0
      ]
    },
    {
      "parameters": {
        "sendTo": "brandon@blazeproperty.com, tammie@blazeproperty.com, ashlie@blazeproperty.com",
        "subject": "={{ $json.subject }}",
        "message": "={{ $json.html }}",
        "options": {}
      },
      "type": "n8n-nodes-base.gmail",
      "typeVersion": 2.2,
      "position": [
        800,
        224
      ],
      "id": "778b27dc-93bd-42f1-b22a-4512d1d83788",
      "name": "Send a message",
      "webhookId": "50bee5bb-e87d-4736-ac83-929755f1e733",
      "credentials": {
        "gmailOAuth2": {
          "id": "L5rzlMgd96udEdLH",
          "name": "Brandon@blazeproperty.com"
        }
      }
    },
    {
      "parameters": {
        "jsCode": "const rows = items.map(item => item.json);\n\nconst money = (value) =>\n  Number(value || 0).toLocaleString(\"en-US\", {\n    style: \"currency\",\n    currency: \"USD\",\n  });\n\nconst text = (value) =>\n  value && String(value).trim() ? String(value).trim() : \"—\";\n\nconst total = rows.reduce(\n  (acc, row) => {\n    acc.vacant_units += Number(row.vacant_units || 0);\n    acc.ready_vacants += Number(row.ready_vacants || 0);\n    acc.not_ready_vacants += Number(row.not_ready_vacants || 0);\n    acc.delinquent_count += Number(row.delinquent_count || 0);\n    acc.delinquent_amount += Number(row.delinquent_amount || 0);\n    acc.turns_in_progress += Number(row.turns_in_progress || 0);\n    acc.work_orders_over_7_days += Number(row.work_orders_over_7_days || 0);\n    return acc;\n  },\n  {\n    vacant_units: 0,\n    ready_vacants: 0,\n    not_ready_vacants: 0,\n    delinquent_count: 0,\n    delinquent_amount: 0,\n    turns_in_progress: 0,\n    work_orders_over_7_days: 0,\n  }\n);\n\nconst managerName = rows[0]?.manager_name || \"Manager\";\nconst weekStartDate = rows[0]?.week_start_date || \"\";\n\nconst propertySections = rows\n  .map((row) => {\n    const lateBadge = Number(row.late_submission) === 1\n      ? `<span style=\"background:#fff3cd;color:#856404;padding:4px 8px;border-radius:999px;font-size:12px;font-weight:700;\">Late Submission</span>`\n      : \"\";\n\n    return `\n      <div style=\"border:1px solid #d9e2ec;border-radius:10px;margin:18px 0;padding:18px;background:#ffffff;\">\n        <h2 style=\"margin:0 0 6px;font-size:20px;color:#102a43;\">\n          ${text(row.property_name)} ${lateBadge}\n        </h2>\n\n        <table style=\"width:100%;border-collapse:collapse;margin-top:14px;font-size:14px;\">\n          <tr>\n            <td style=\"padding:8px;border-bottom:1px solid #edf2f7;\"><strong>Vacant Units</strong></td>\n            <td style=\"padding:8px;border-bottom:1px solid #edf2f7;\">${row.vacant_units}</td>\n          </tr>\n          <tr>\n            <td style=\"padding:8px;border-bottom:1px solid #edf2f7;\"><strong>Ready Vacants</strong></td>\n            <td style=\"padding:8px;border-bottom:1px solid #edf2f7;\">${row.ready_vacants}</td>\n          </tr>\n          <tr>\n            <td style=\"padding:8px;border-bottom:1px solid #edf2f7;\"><strong>Not Ready Vacants</strong></td>\n            <td style=\"padding:8px;border-bottom:1px solid #edf2f7;\">${row.not_ready_vacants}</td>\n          </tr>\n          <tr>\n            <td style=\"padding:8px;border-bottom:1px solid #edf2f7;\"><strong>Delinquent Count</strong></td>\n            <td style=\"padding:8px;border-bottom:1px solid #edf2f7;\">${row.delinquent_count}</td>\n          </tr>\n          <tr>\n            <td style=\"padding:8px;border-bottom:1px solid #edf2f7;\"><strong>Delinquent Amount</strong></td>\n            <td style=\"padding:8px;border-bottom:1px solid #edf2f7;\">${money(row.delinquent_amount)}</td>\n          </tr>\n          <tr>\n            <td style=\"padding:8px;border-bottom:1px solid #edf2f7;\"><strong>Turns in Progress</strong></td>\n            <td style=\"padding:8px;border-bottom:1px solid #edf2f7;\">${row.turns_in_progress}</td>\n          </tr>\n          <tr>\n            <td style=\"padding:8px;\"><strong>Work Orders Over 7 Days</strong></td>\n            <td style=\"padding:8px;\">${row.work_orders_over_7_days}</td>\n          </tr>\n        </table>\n\n        <div style=\"margin-top:16px;\">\n          <p><strong>Biggest Issue:</strong><br>${text(row.biggest_issue_text)}</p>\n          <p><strong>Help Needed:</strong><br>${text(row.help_needed_text)}</p>\n          <p><strong>Struggling Units / Leasing Notes:</strong><br>${text(row.struggling_units_text)}</p>\n        </div>\n      </div>\n    `;\n  })\n  .join(\"\");\n\nconst html = `\n<!DOCTYPE html>\n<html>\n<body style=\"margin:0;padding:0;background:#f5f7fa;font-family:Arial,Helvetica,sans-serif;color:#243b53;\">\n  <div style=\"max-width:760px;margin:0 auto;padding:24px;\">\n    <div style=\"background:#102a43;color:#ffffff;padding:22px;border-radius:12px 12px 0 0;\">\n      <h1 style=\"margin:0;font-size:24px;\">Weekly Manager Report</h1>\n      <p style=\"margin:8px 0 0;\">${managerName} — Week of ${weekStartDate}</p>\n    </div>\n\n    <div style=\"background:#ffffff;padding:18px;border-left:1px solid #d9e2ec;border-right:1px solid #d9e2ec;\">\n      <h2 style=\"margin-top:0;color:#102a43;\">Snapshot Summary</h2>\n\n      <table style=\"width:100%;border-collapse:collapse;font-size:14px;\">\n        <tr>\n          <td style=\"padding:8px;border-bottom:1px solid #edf2f7;\"><strong>Total Vacants</strong></td>\n          <td style=\"padding:8px;border-bottom:1px solid #edf2f7;\">${total.vacant_units}</td>\n        </tr>\n        <tr>\n          <td style=\"padding:8px;border-bottom:1px solid #edf2f7;\"><strong>Ready / Not Ready</strong></td>\n          <td style=\"padding:8px;border-bottom:1px solid #edf2f7;\">${total.ready_vacants} / ${total.not_ready_vacants}</td>\n        </tr>\n        <tr>\n          <td style=\"padding:8px;border-bottom:1px solid #edf2f7;\"><strong>Total Delinquent Accounts</strong></td>\n          <td style=\"padding:8px;border-bottom:1px solid #edf2f7;\">${total.delinquent_count}</td>\n        </tr>\n        <tr>\n          <td style=\"padding:8px;border-bottom:1px solid #edf2f7;\"><strong>Total Delinquent Amount</strong></td>\n          <td style=\"padding:8px;border-bottom:1px solid #edf2f7;\">${money(total.delinquent_amount)}</td>\n        </tr>\n        <tr>\n          <td style=\"padding:8px;border-bottom:1px solid #edf2f7;\"><strong>Turns in Progress</strong></td>\n          <td style=\"padding:8px;border-bottom:1px solid #edf2f7;\">${total.turns_in_progress}</td>\n        </tr>\n        <tr>\n          <td style=\"padding:8px;\"><strong>Work Orders Over 7 Days</strong></td>\n          <td style=\"padding:8px;\">${total.work_orders_over_7_days}</td>\n        </tr>\n      </table>\n\n      ${propertySections}\n    </div>\n\n    <div style=\"background:#eef2f7;padding:14px;border-radius:0 0 12px 12px;border:1px solid #d9e2ec;font-size:12px;color:#52606d;\">\n      This email is generated from the weekly manager reporting baseline.\n    </div>\n  </div>\n</body>\n</html>\n`;\n\nreturn [\n  {\n    json: {\n      manager_name: managerName,\n      week_start_date: weekStartDate,\n      subject: `Weekly Manager Report - ${managerName} - ${weekStartDate}`,\n      html,\n    },\n  },\n];"
      },
      "type": "n8n-nodes-base.code",
      "typeVersion": 2,
      "position": [
        496,
        0
      ],
      "id": "3aeb08c1-2d63-4aea-b111-a91c7fbd0fd0",
      "name": "Code in JavaScript"
    }
  ],
  "connections": {
    "Webhook": {
      "main": [
        [
          {
            "node": "Validate and Expand Rows",
            "type": "main",
            "index": 0
          }
        ]
      ]
    },
    "Validate and Expand Rows": {
      "main": [
        [
          {
            "node": "Insert Weekly Report Rows",
            "type": "main",
            "index": 0
          },
          {
            "node": "Code in JavaScript",
            "type": "main",
            "index": 0
          }
        ]
      ]
    },
    "Insert Weekly Report Rows": {
      "main": [
        [
          {
            "node": "Respond Success",
            "type": "main",
            "index": 0
          }
        ]
      ]
    },
    "Send a message": {
      "main": [
        []
      ]
    },
    "Code in JavaScript": {
      "main": [
        [
          {
            "node": "Send a message",
            "type": "main",
            "index": 0
          }
        ]
      ]
    }
  },
  "settings": {
    "executionOrder": "v1",
    "binaryMode": "separate",
    "timeSavedMode": "fixed",
    "errorWorkflow": "3WJZrZsLJqgg1EIM",
    "saveDataSuccessExecution": "none",
    "callerPolicy": "workflowsFromSameOwner",
    "availableInMCP": false,
    "timeSavedPerExecution": 5
  },
  "staticData": null,
  "meta": {
    "templateCredsSetupCompleted": true
  },
  "pinData": {},
  "versionId": "0a24c148-eb06-4661-b0c1-997593de4d69",
  "activeVersionId": "0a24c148-eb06-4661-b0c1-997593de4d69",
  "triggerCount": 1,
  "shared": [
    {
      "updatedAt": "2026-04-22T15:34:01.105Z",
      "createdAt": "2026-04-22T15:34:01.105Z",
      "role": "workflow:owner",
      "workflowId": "SDSoESzsSfL87W36",
      "projectId": "4YBqTudLOBUQfTvU"
    }
  ],
  "activeVersion": {
    "updatedAt": "2026-05-05T14:24:09.486Z",
    "createdAt": "2026-05-05T14:24:00.639Z",
    "versionId": "0a24c148-eb06-4661-b0c1-997593de4d69",
    "workflowId": "SDSoESzsSfL87W36",
    "nodes": [
      {
        "parameters": {
          "httpMethod": "POST",
          "path": "manager-weekly-report-intake",
          "responseMode": "responseNode",
          "options": {}
        },
        "id": "31cf6e68-c1ea-4702-a698-fd23dcd46724",
        "name": "Webhook",
        "type": "n8n-nodes-base.webhook",
        "typeVersion": 2,
        "position": [
          0,
          0
        ],
        "webhookId": "5540db84-f8fc-41ef-abb0-a2f02339555d"
      },
      {
        "parameters": {
          "jsCode": "\nconst body = $json.body ?? $json;\nconst portfolioMap = {\n  \"Breanna\": [\"Courtyard\", \"Adobe\", \"NorthPark\"],\n  \"Amy\": [\"Jefferson\", \"Riveredge\", \"Crosskeys\"],\n  \"Debbie\": [\"Sagebrush\"],\n  \"Dede\": [\"Westminster\", \"Broadstone\", \"Nelson\"],\n  \"Shelbie/Chris\": [\"Oak Terrace\"],\n  \"Ashlie\": [\"Single Families and Small Multi\"]\n};\n\nfunction isMonday(dateStr) {\n  const d = new Date(`${dateStr}T00:00:00`);\n  return !Number.isNaN(d.getTime()) && d.getDay() === 1;\n}\n\nfunction makeUuid() {\n  return 'xxxxxxxx-xxxx-4xxx-yxxx-xxxxxxxxxxxx'.replace(/[xy]/g, c => {\n    const r = Math.random() * 16 | 0;\n    const v = c === 'x' ? r : (r & 0x3 | 0x8);\n    return v.toString(16);\n  });\n}\n\nconst requiredTop = ['manager_name', 'week_start_date', 'submitted_at', 'properties'];\nfor (const field of requiredTop) {\n  if (!(field in body)) {\n    throw new Error(`Missing top-level field: ${field}`);\n  }\n}\n\nif (!portfolioMap[body.manager_name]) {\n  throw new Error(`Invalid manager_name: ${body.manager_name}`);\n}\n\nif (!isMonday(body.week_start_date)) {\n  throw new Error('week_start_date must be a Monday');\n}\n\nif (!Array.isArray(body.properties) || body.properties.length === 0) {\n  throw new Error('properties must be a non-empty array');\n}\n\nconst expectedProperties = new Set(portfolioMap[body.manager_name]);\nconst seenProperties = new Set();\n\nconst submittedAt = new Date(body.submitted_at);\nif (Number.isNaN(submittedAt.getTime())) {\n  throw new Error('submitted_at must be a valid ISO timestamp');\n}\n\nconst mondayCutoff = new Date(`${body.week_start_date}T10:00:00-05:00`);\nconst lateSubmission = submittedAt > mondayCutoff ? 1 : 0;\n\nconst rows = body.properties.map((row) => {\n  const requiredNumeric = [\n    'vacant_units',\n    'ready_vacants',\n    'not_ready_vacants',\n    'delinquent_count',\n    'delinquent_amount',\n    'turns_in_progress',\n    'work_orders_over_7_days'\n  ];\n  const requiredText = ['property_name', 'biggest_issue_text', 'help_needed_text'];\n\n  for (const field of requiredNumeric) {\n    if (!(field in row)) throw new Error(`Missing required numeric field: ${field}`);\n    const num = Number(row[field]);\n    if (Number.isNaN(num) || num < 0) throw new Error(`Invalid numeric value for ${field} on ${row.property_name}`);\n  }\n\n  for (const field of requiredText) {\n    if (!(field in row) || !String(row[field]).trim()) {\n      throw new Error(`Missing required text field: ${field} on ${row.property_name ?? 'unknown property'}`);\n    }\n  }\n\n  if (Number(row.vacant_units) !== Number(row.ready_vacants) + Number(row.not_ready_vacants)) {\n    throw new Error(`Vacancy split mismatch on ${row.property_name}`);\n  }\n\n  if (!expectedProperties.has(row.property_name)) {\n    throw new Error(`Property ${row.property_name} is not assigned to ${body.manager_name}`);\n  }\n  if (seenProperties.has(row.property_name)) {\n    throw new Error(`Duplicate property row: ${row.property_name}`);\n  }\n  seenProperties.add(row.property_name);\n\n  return {\n    id: makeUuid(),\n    manager_name: body.manager_name,\n    week_start_date: body.week_start_date,\n    property_name: row.property_name,\n    vacant_units: Number(row.vacant_units),\n    ready_vacants: Number(row.ready_vacants),\n    not_ready_vacants: Number(row.not_ready_vacants),\n    delinquent_count: Number(row.delinquent_count),\n    delinquent_amount: Number(Number(row.delinquent_amount).toFixed(2)),\n    turns_in_progress: Number(row.turns_in_progress),\n    work_orders_over_7_days: Number(row.work_orders_over_7_days),\n    biggest_issue_text: String(row.biggest_issue_text).trim(),\n    help_needed_text: String(row.help_needed_text).trim(),\n    struggling_units_text: row.struggling_units_text ? String(row.struggling_units_text).trim() : null,\n    late_submission: lateSubmission,\n    created_at: new Date().toISOString().slice(0, 19).replace('T', ' ')\n  };\n});\n\nfor (const property of expectedProperties) {\n  if (!seenProperties.has(property)) {\n    throw new Error(`Missing assigned property row: ${property}`);\n  }\n}\n\nreturn rows.map(r => ({ json: r }));\n"
        },
        "id": "36dc31fb-8992-4130-9320-c66c9225c684",
        "name": "Validate and Expand Rows",
        "type": "n8n-nodes-base.code",
        "typeVersion": 2,
        "position": [
          288,
          0
        ]
      },
      {
        "parameters": {
          "operation": "executeQuery",
          "query": "\nINSERT INTO manager_weekly_reports (\n  id,\n  manager_name,\n  week_start_date,\n  property_name,\n  vacant_units,\n  ready_vacants,\n  not_ready_vacants,\n  delinquent_count,\n  delinquent_amount,\n  turns_in_progress,\n  work_orders_over_7_days,\n  biggest_issue_text,\n  help_needed_text,\n  struggling_units_text,\n  late_submission,\n  created_at\n) VALUES (\n  $1,$2,$3,$4,$5,$6,$7,$8,$9,$10,$11,$12,$13,$14,$15,$16\n);\n",
          "options": {
            "queryReplacement": "={{\n[\n  $json.id,\n  $json.manager_name,\n  $json.week_start_date,\n  $json.property_name,\n  $json.vacant_units,\n  $json.ready_vacants,\n  $json.not_ready_vacants,\n  $json.delinquent_count,\n  $json.delinquent_amount,\n  $json.turns_in_progress,\n  $json.work_orders_over_7_days,\n  $json.biggest_issue_text,\n  $json.help_needed_text,\n  $json.struggling_units_text || null,\n  $json.late_submission,\n  $json.created_at\n]\n}}"
          }
        },
        "id": "708d1b45-6573-40c0-a4ea-28fa6c6ff12f",
        "name": "Insert Weekly Report Rows",
        "type": "n8n-nodes-base.mySql",
        "typeVersion": 2.5,
        "position": [
          768,
          0
        ],
        "credentials": {
          "mySql": {
            "id": "f3UzvmAj6M8o27XN",
            "name": "Blaze_Ops Database"
          }
        }
      },
      {
        "parameters": {
          "respondWith": "json",
          "responseBody": "={\"status\":\"ok\",\"rows_inserted\": {{$items().length}} }",
          "options": {}
        },
        "id": "f4b4c3d3-8a8b-4089-b28a-a6286eddda84",
        "name": "Respond Success",
        "type": "n8n-nodes-base.respondToWebhook",
        "typeVersion": 1.1,
        "position": [
          1072,
          0
        ]
      },
      {
        "parameters": {
          "sendTo": "brandon@blazeproperty.com, tammie@blazeproperty.com, ashlie@blazeproperty.com",
          "subject": "={{ $json.subject }}",
          "message": "={{ $json.html }}",
          "options": {}
        },
        "type": "n8n-nodes-base.gmail",
        "typeVersion": 2.2,
        "position": [
          800,
          224
        ],
        "id": "778b27dc-93bd-42f1-b22a-4512d1d83788",
        "name": "Send a message",
        "webhookId": "50bee5bb-e87d-4736-ac83-929755f1e733",
        "credentials": {
          "gmailOAuth2": {
            "id": "L5rzlMgd96udEdLH",
            "name": "Brandon@blazeproperty.com"
          }
        }
      },
      {
        "parameters": {
          "jsCode": "const rows = items.map(item => item.json);\n\nconst money = (value) =>\n  Number(value || 0).toLocaleString(\"en-US\", {\n    style: \"currency\",\n    currency: \"USD\",\n  });\n\nconst text = (value) =>\n  value && String(value).trim() ? String(value).trim() : \"—\";\n\nconst total = rows.reduce(\n  (acc, row) => {\n    acc.vacant_units += Number(row.vacant_units || 0);\n    acc.ready_vacants += Number(row.ready_vacants || 0);\n    acc.not_ready_vacants += Number(row.not_ready_vacants || 0);\n    acc.delinquent_count += Number(row.delinquent_count || 0);\n    acc.delinquent_amount += Number(row.delinquent_amount || 0);\n    acc.turns_in_progress += Number(row.turns_in_progress || 0);\n    acc.work_orders_over_7_days += Number(row.work_orders_over_7_days || 0);\n    return acc;\n  },\n  {\n    vacant_units: 0,\n    ready_vacants: 0,\n    not_ready_vacants: 0,\n    delinquent_count: 0,\n    delinquent_amount: 0,\n    turns_in_progress: 0,\n    work_orders_over_7_days: 0,\n  }\n);\n\nconst managerName = rows[0]?.manager_name || \"Manager\";\nconst weekStartDate = rows[0]?.week_start_date || \"\";\n\nconst propertySections = rows\n  .map((row) => {\n    const lateBadge = Number(row.late_submission) === 1\n      ? `<span style=\"background:#fff3cd;color:#856404;padding:4px 8px;border-radius:999px;font-size:12px;font-weight:700;\">Late Submission</span>`\n      : \"\";\n\n    return `\n      <div style=\"border:1px solid #d9e2ec;border-radius:10px;margin:18px 0;padding:18px;background:#ffffff;\">\n        <h2 style=\"margin:0 0 6px;font-size:20px;color:#102a43;\">\n          ${text(row.property_name)} ${lateBadge}\n        </h2>\n\n        <table style=\"width:100%;border-collapse:collapse;margin-top:14px;font-size:14px;\">\n          <tr>\n            <td style=\"padding:8px;border-bottom:1px solid #edf2f7;\"><strong>Vacant Units</strong></td>\n            <td style=\"padding:8px;border-bottom:1px solid #edf2f7;\">${row.vacant_units}</td>\n          </tr>\n          <tr>\n            <td style=\"padding:8px;border-bottom:1px solid #edf2f7;\"><strong>Ready Vacants</strong></td>\n            <td style=\"padding:8px;border-bottom:1px solid #edf2f7;\">${row.ready_vacants}</td>\n          </tr>\n          <tr>\n            <td style=\"padding:8px;border-bottom:1px solid #edf2f7;\"><strong>Not Ready Vacants</strong></td>\n            <td style=\"padding:8px;border-bottom:1px solid #edf2f7;\">${row.not_ready_vacants}</td>\n          </tr>\n          <tr>\n            <td style=\"padding:8px;border-bottom:1px solid #edf2f7;\"><strong>Delinquent Count</strong></td>\n            <td style=\"padding:8px;border-bottom:1px solid #edf2f7;\">${row.delinquent_count}</td>\n          </tr>\n          <tr>\n            <td style=\"padding:8px;border-bottom:1px solid #edf2f7;\"><strong>Delinquent Amount</strong></td>\n            <td style=\"padding:8px;border-bottom:1px solid #edf2f7;\">${money(row.delinquent_amount)}</td>\n          </tr>\n          <tr>\n            <td style=\"padding:8px;border-bottom:1px solid #edf2f7;\"><strong>Turns in Progress</strong></td>\n            <td style=\"padding:8px;border-bottom:1px solid #edf2f7;\">${row.turns_in_progress}</td>\n          </tr>\n          <tr>\n            <td style=\"padding:8px;\"><strong>Work Orders Over 7 Days</strong></td>\n            <td style=\"padding:8px;\">${row.work_orders_over_7_days}</td>\n          </tr>\n        </table>\n\n        <div style=\"margin-top:16px;\">\n          <p><strong>Biggest Issue:</strong><br>${text(row.biggest_issue_text)}</p>\n          <p><strong>Help Needed:</strong><br>${text(row.help_needed_text)}</p>\n          <p><strong>Struggling Units / Leasing Notes:</strong><br>${text(row.struggling_units_text)}</p>\n        </div>\n      </div>\n    `;\n  })\n  .join(\"\");\n\nconst html = `\n<!DOCTYPE html>\n<html>\n<body style=\"margin:0;padding:0;background:#f5f7fa;font-family:Arial,Helvetica,sans-serif;color:#243b53;\">\n  <div style=\"max-width:760px;margin:0 auto;padding:24px;\">\n    <div style=\"background:#102a43;color:#ffffff;padding:22px;border-radius:12px 12px 0 0;\">\n      <h1 style=\"margin:0;font-size:24px;\">Weekly Manager Report</h1>\n      <p style=\"margin:8px 0 0;\">${managerName} — Week of ${weekStartDate}</p>\n    </div>\n\n    <div style=\"background:#ffffff;padding:18px;border-left:1px solid #d9e2ec;border-right:1px solid #d9e2ec;\">\n      <h2 style=\"margin-top:0;color:#102a43;\">Snapshot Summary</h2>\n\n      <table style=\"width:100%;border-collapse:collapse;font-size:14px;\">\n        <tr>\n          <td style=\"padding:8px;border-bottom:1px solid #edf2f7;\"><strong>Total Vacants</strong></td>\n          <td style=\"padding:8px;border-bottom:1px solid #edf2f7;\">${total.vacant_units}</td>\n        </tr>\n        <tr>\n          <td style=\"padding:8px;border-bottom:1px solid #edf2f7;\"><strong>Ready / Not Ready</strong></td>\n          <td style=\"padding:8px;border-bottom:1px solid #edf2f7;\">${total.ready_vacants} / ${total.not_ready_vacants}</td>\n        </tr>\n        <tr>\n          <td style=\"padding:8px;border-bottom:1px solid #edf2f7;\"><strong>Total Delinquent Accounts</strong></td>\n          <td style=\"padding:8px;border-bottom:1px solid #edf2f7;\">${total.delinquent_count}</td>\n        </tr>\n        <tr>\n          <td style=\"padding:8px;border-bottom:1px solid #edf2f7;\"><strong>Total Delinquent Amount</strong></td>\n          <td style=\"padding:8px;border-bottom:1px solid #edf2f7;\">${money(total.delinquent_amount)}</td>\n        </tr>\n        <tr>\n          <td style=\"padding:8px;border-bottom:1px solid #edf2f7;\"><strong>Turns in Progress</strong></td>\n          <td style=\"padding:8px;border-bottom:1px solid #edf2f7;\">${total.turns_in_progress}</td>\n        </tr>\n        <tr>\n          <td style=\"padding:8px;\"><strong>Work Orders Over 7 Days</strong></td>\n          <td style=\"padding:8px;\">${total.work_orders_over_7_days}</td>\n        </tr>\n      </table>\n\n      ${propertySections}\n    </div>\n\n    <div style=\"background:#eef2f7;padding:14px;border-radius:0 0 12px 12px;border:1px solid #d9e2ec;font-size:12px;color:#52606d;\">\n      This email is generated from the weekly manager reporting baseline.\n    </div>\n  </div>\n</body>\n</html>\n`;\n\nreturn [\n  {\n    json: {\n      manager_name: managerName,\n      week_start_date: weekStartDate,\n      subject: `Weekly Manager Report - ${managerName} - ${weekStartDate}`,\n      html,\n    },\n  },\n];"
        },
        "type": "n8n-nodes-base.code",
        "typeVersion": 2,
        "position": [
          496,
          0
        ],
        "id": "3aeb08c1-2d63-4aea-b111-a91c7fbd0fd0",
        "name": "Code in JavaScript"
      }
    ],
    "connections": {
      "Webhook": {
        "main": [
          [
            {
              "node": "Validate and Expand Rows",
              "type": "main",
              "index": 0
            }
          ]
        ]
      },
      "Validate and Expand Rows": {
        "main": [
          [
            {
              "node": "Insert Weekly Report Rows",
              "type": "main",
              "index": 0
            },
            {
              "node": "Code in JavaScript",
              "type": "main",
              "index": 0
            }
          ]
        ]
      },
      "Insert Weekly Report Rows": {
        "main": [
          [
            {
              "node": "Respond Success",
              "type": "main",
              "index": 0
            }
          ]
        ]
      },
      "Send a message": {
        "main": [
          []
        ]
      },
      "Code in JavaScript": {
        "main": [
          [
            {
              "node": "Send a message",
              "type": "main",
              "index": 0
            }
          ]
        ]
      }
    },
    "authors": "Brandon Stewart",
    "name": "Version 0a24c148",
    "description": "",
    "autosaved": true
  },
  "tags": [
    {
      "updatedAt": "2026-04-23T12:40:11.767Z",
      "createdAt": "2026-04-23T12:40:11.767Z",
      "id": "nwYcKrWKYFiGYTIf",
      "name": "Meeting Workflow"
    }
  ]
}